CHANGES.rst
MANIFEST.in
README.rst
TODO.rst
setup.cfg
setup.py
bin/tml-filter-catlang.py
bin/tml-filter-raw.py
bin/tml-generate-features.py
bin/tml-hstack.py
bin/tml-preprocess.py
experiments/Word2Vec.py
experiments/exp0_preprocessing.py
experiments/exp0_toydata.py
experiments/exp1-compare-features.py
experiments/exp1a-selective_auc.py
experiments/exp2-compare-classifiers.py
experiments/exp3-compare-regressors.py
experiments/graph_from_data_backup.py
tests/__init__.py
tests/evaluation_tests.py
tests/features_tests.py
tests/filtering_tests.py
tests/preprocessing_tests.py
tests/targets_tests.py
tests/utility_tests.py
twistml/__init__.py
twistml.egg-info/PKG-INFO
twistml.egg-info/SOURCES.txt
twistml.egg-info/dependency_links.txt
twistml.egg-info/not-zip-safe
twistml.egg-info/requires.txt
twistml.egg-info/top_level.txt
twistml/evaluation/__init__.py
twistml/evaluation/evaluation.py
twistml/features/__init__.py
twistml/features/combine.py
twistml/features/countvector_transformer.py
twistml/features/doc2vec_transformer.py
twistml/features/feature_transformer.py
twistml/features/sentiment_transformer.py
twistml/features/window.py
twistml/filtering/__init__.py
twistml/filtering/category.py
twistml/filtering/language.py
twistml/filtering/rawtweets.py
twistml/filtering/ldig/__init__.py
twistml/filtering/ldig/da.py
twistml/filtering/ldig/ldig.py
twistml/filtering/ldig/modeldata/doublearray.npz
twistml/filtering/ldig/modeldata/features
twistml/filtering/ldig/modeldata/labels.json
twistml/filtering/ldig/modeldata/parameters.npy
twistml/preprocessing/__init__.py
twistml/preprocessing/preprocessing.py
twistml/targets/__init__.py
twistml/targets/rawstockdata.py
twistml/utility/__init__.py
twistml/utility/plotting.py
twistml/utility/toydata.py
twistml/utility/utility.py