Metadata-Version: 1.1
Name: twistml
Version: 0.9
Summary: TWItter STock market Machine Learning package
Home-page: https://bitbucket.org/madmat3001/twistml.git
Author: Matthias Manhertz
Author-email: m@nhertz.de
License: MIT
Keywords: twitter stock market machine learning
Platform: any
Classifier: Development Status :: 4 - Beta
Classifier: License :: OSI Approved :: MIT License
Classifier: Programming Language :: Python :: 2.7
Classifier: Topic :: Scientific/Engineering :: Information Analysis
Classifier: Intended Audience :: Science/Research
Classifier: Natural Language :: English
Classifier: Operating System :: OS Independent
